node_utils/__init__.py
node_utils/errors.py
node_utils/node.py
node_utils/py.typed
node_utils/typing.py
node_utils/version.py
node_utils/explorers/__init__.py
node_utils/explorers/base.py
node_utils/explorers/optimizer.py
node_utils/explorers/transformer.py
node_utils/explorers/visitor.py
node_utils-0.2.1.dist-info/LICENSE
node_utils-0.2.1.dist-info/METADATA
node_utils-0.2.1.dist-info/WHEEL
node_utils-0.2.1.dist-info/top_level.txt
node_utils-0.2.1.dist-info/RECORD
