Metadata-Version: 2.1
Name: node-utils
Version: 0.2.1
Summary: node-utils: Utility classes and functions for working with generic abstract syntax tree (AST) nodes.
Home-page: https://github.com/ApeWorX/node-utils
Author: ApeWorX Ltd.
Author-email: admin@apeworx.io
License: Apache License 2.0
Keywords: ast nodes compiler
Platform: UNKNOWN
Classifier: Development Status :: 3 - Alpha
Classifier: Intended Audience :: Developers
Classifier: License :: OSI Approved :: Apache Software License
Classifier: Natural Language :: English
Classifier: Programming Language :: Python :: 3
Classifier: Programming Language :: Python :: 3.6
Classifier: Programming Language :: Python :: 3.7
Classifier: Programming Language :: Python :: 3.8
Classifier: Programming Language :: Python :: 3.9
Requires-Python: >=3.6, <4
Requires-Dist: dataclassy (<0.8.0,>=0.7.2)
Provides-Extra: dev
Requires-Dist: pytest (<7.0,>=6.0) ; extra == 'dev'
Requires-Dist: pytest-xdist ; extra == 'dev'
Requires-Dist: pytest-cov ; extra == 'dev'
Requires-Dist: black (<21.0,>=20.8b1) ; extra == 'dev'
Requires-Dist: mypy (<1.0,>=0.800) ; extra == 'dev'
Requires-Dist: flake8 (<4.0,>=3.8.3) ; extra == 'dev'
Requires-Dist: isort (<6.0,>=5.7.0) ; extra == 'dev'
Requires-Dist: Sphinx (<4,>=3.4.3) ; extra == 'dev'
Requires-Dist: sphinx-rtd-theme (<1,>=0.1.9) ; extra == 'dev'
Requires-Dist: towncrier (<20,>=19.2.0) ; extra == 'dev'
Requires-Dist: setuptools ; extra == 'dev'
Requires-Dist: setuptools-scm ; extra == 'dev'
Requires-Dist: wheel ; extra == 'dev'
Requires-Dist: twine ; extra == 'dev'
Requires-Dist: commitizen ; extra == 'dev'
Requires-Dist: pytest-watch ; extra == 'dev'
Requires-Dist: IPython ; extra == 'dev'
Requires-Dist: ipdb ; extra == 'dev'
Provides-Extra: doc
Requires-Dist: Sphinx (<4,>=3.4.3) ; extra == 'doc'
Requires-Dist: sphinx-rtd-theme (<1,>=0.1.9) ; extra == 'doc'
Requires-Dist: towncrier (<20,>=19.2.0) ; extra == 'doc'
Provides-Extra: lint
Requires-Dist: black (<21.0,>=20.8b1) ; extra == 'lint'
Requires-Dist: mypy (<1.0,>=0.800) ; extra == 'lint'
Requires-Dist: flake8 (<4.0,>=3.8.3) ; extra == 'lint'
Requires-Dist: isort (<6.0,>=5.7.0) ; extra == 'lint'
Provides-Extra: release
Requires-Dist: setuptools ; extra == 'release'
Requires-Dist: setuptools-scm ; extra == 'release'
Requires-Dist: wheel ; extra == 'release'
Requires-Dist: twine ; extra == 'release'
Provides-Extra: test
Requires-Dist: pytest (<7.0,>=6.0) ; extra == 'test'
Requires-Dist: pytest-xdist ; extra == 'test'
Requires-Dist: pytest-cov ; extra == 'test'
